MANIFEST.in
README.rst
requirements.txt
setup.py
Mr_Repo.egg-info/PKG-INFO
Mr_Repo.egg-info/SOURCES.txt
Mr_Repo.egg-info/dependency_links.txt
Mr_Repo.egg-info/entry_points.txt
Mr_Repo.egg-info/requires.txt
Mr_Repo.egg-info/top_level.txt
mr_repo/__init__.py
mr_repo/main.py
mr_repo/repossesser.py
mr_repo/version.py