Metadata-Version: 1.0
Name: Mr-Repo
Version: 0.2.10
Summary: Mr. Repo - A simple repo management system
Home-page: http://pypi.python.org/pypi/Mr-Repo/0.2.10
Author: Ryan McGowan
Author-email: ryan@ryanmcg.com
License: UNKNOWN
Platform: UNKNOWN
Classifier: Development Status :: 4 - Beta
Classifier: Programming Language :: Python
Classifier: Programming Language :: Python :: 2
